flask_paseto/__init__.py
flask_paseto/config.py
flask_paseto/local_paseto.py
flask_paseto/public_paseto.py
flask_paseto/utils.py
Flask_PASETO-0.0.1.dist-info/LICENSE
Flask_PASETO-0.0.1.dist-info/METADATA
Flask_PASETO-0.0.1.dist-info/WHEEL
Flask_PASETO-0.0.1.dist-info/top_level.txt
Flask_PASETO-0.0.1.dist-info/RECORD
