Metadata-Version: 2.1
Name: Flask-PASETO
Version: 0.0.1
Summary: Paseto integration for flask
Home-page: UNKNOWN
Author: Akerele Abraham
License: MIT
Platform: UNKNOWN
